<?xml version="1.0" encoding="UTF-8"?>
<root><Source> Twitter</Source><Date> Mi 2019-05-08</Date><Place> Berlin</Place><Title> </Title><Subtitle> </Subtitle><Author> @renetuninger</Author><Article> #RotGruen bis zum Exzess: #Drogendealer bekommen jetzt im #GoerlitzerPark wie auf jedem Wochenmarkt feste Standplaetze mit Bodenmarkierungen zugewiesen! #Berlin #Rechtsstaat? https://www.t-online.de/nachrichten/panorama/kriminalitaet/id_85717296/goerlitzer-park-es-gibt-nun-flaechen-fuer-drogendealer.html</Article><Additional> </Additional><Link> https://twitter.com/ReneTruninger/status/1126127834425065472</Link></root>